cyhole/__init__.py
cyhole/birdeye/__init__.py
cyhole/birdeye/client.py
cyhole/birdeye/exception.py
cyhole/birdeye/interaction.py
cyhole/birdeye/param.py
cyhole/birdeye/schema.py
cyhole/core/__init__.py
cyhole/core/client.py
cyhole/core/exception.py
cyhole/core/interaction.py
cyhole/core/param.py
cyhole/core/token/__init__.py
cyhole/core/token/ethereum.py
cyhole/core/token/solana.py
cyhole/jupiter/__init__.py
cyhole/jupiter/client.py
cyhole/jupiter/exception.py
cyhole/jupiter/interaction.py
cyhole/jupiter/param.py
cyhole/jupiter/schema.py
cyhole/solana_fm/__init__.py
cyhole/solana_fm/client.py
cyhole/solana_fm/exception.py
cyhole/solana_fm/interaction.py
cyhole/solana_fm/param.py
cyhole/solana_fm/schema.py
cyhole/solscan/__init__.py
cyhole/solscan/v1/__init__.py
cyhole/solscan/v1/client.py
cyhole/solscan/v1/exception.py
cyhole/solscan/v1/interaction.py
cyhole/solscan/v1/param.py
cyhole/solscan/v1/schema.py
cyhole/solscan/v2/__init__.py
cyhole/solscan/v2/client.py
cyhole/solscan/v2/exception.py
cyhole/solscan/v2/interaction.py
cyhole/solscan/v2/param.py
cyhole/solscan/v2/schema.py
cyhole-0.2.4.dist-info/METADATA
cyhole-0.2.4.dist-info/WHEEL
cyhole-0.2.4.dist-info/licenses/LICENSE
cyhole-0.2.4.dist-info/RECORD
