Metadata-Version: 2.3
Name: cyhole
Version: 0.2.4
Summary: cyhole, designed to help python's developers to interact to the most popular external API services in crypto and create automation processes.
Project-URL: Homepage, https://github.com/zazza123/cyhole
Project-URL: Repository, https://github.com/zazza123/cyhole
Project-URL: Documentation, https://zazza123.github.io/cyhole
Author: Andrea Zanini
License-File: LICENSE
Classifier: Development Status :: 1 - Planning
Classifier: Environment :: Web Environment
Classifier: Framework :: Pydantic
Classifier: Intended Audience :: Developers
Classifier: Intended Audience :: Financial and Insurance Industry
Classifier: Intended Audience :: Information Technology
Classifier: License :: OSI Approved :: MIT License
Classifier: Operating System :: OS Independent
Classifier: Programming Language :: Python
Classifier: Programming Language :: Python :: 3
Classifier: Programming Language :: Python :: 3.12
Requires-Python: >=3.12
Requires-Dist: aiohttp>=3.9.5
Requires-Dist: pydantic>=2.7.0
Requires-Dist: requests>=2.31.0
